<?xml version="1.0" encoding="UTF-8"?>
<!-- https://circleci.com/gh/rgleason/vdr_pi/6636 -->
<plugin version="1">
  <name> VDR </name>
  <version> 1.4.0.0+6636.81bace2 </version>
  <release> 0 </release>
  <summary> Voyage Data Recorder </summary>

  <api-version> 1.18 </api-version>
  <open-source> yes </open-source>
  <author> Rick Gleason </author>
  <source>  </source>
  <info-url> https://opencpn.org/OpenCPN/plugins/vdr.html </info-url>

  <description> A Voyage Data Recorder (VDR) to record and play NMEA files.
Save NMEA stream to a file.  Replay NMEA stream previously saved. Used to test plugins.
 </description>

  <target>darwin-wx32</target>
  <target-version>10</target-version>
  <target-arch>arm64;x86_64</target-arch>
  <tarball-url> https://dl.cloudsmith.io/public/opencpn/vdr-alpha/raw/names/VDR-1.4-darwin-wx32-universal-10-tarball/versions/1.4.0.0+6636.81bace2/VDR-1.4.0.0+6636.81bace2_darwin-wx32-10-arm64-x86_64.tar.gz </tarball-url>
  <tarball-checksum> d3e2f7ae31661a199aff94ade6863ee6f5993ea4c529721d3540d98f00488524 </tarball-checksum>
</plugin>
